botstat/__init__.py
botstat/botstat.py
botstat/log_processing.py
botstat/mail.py
botstat-0.1.2.dist-info/METADATA
botstat-0.1.2.dist-info/RECORD
botstat-0.1.2.dist-info/WHEEL
botstat-0.1.2.dist-info/entry_points.txt
botstat-0.1.2.dist-info/top_level.txt
