Metadata-Version: 2.1
Name: botstat
Version: 0.1.2
Summary: Search engine analyser for nginx/apache web servers
Home-page: https://www.endurantdevs.com
Author: Endurant Devs
Author-email: info@endurantdevs.com
License: MIT
Keywords: cli apache nginx system
Platform: UNKNOWN
Classifier: Development Status :: 4 - Beta
Classifier: License :: OSI Approved :: MIT License
Classifier: Environment :: Console
Classifier: Intended Audience :: Developers
Classifier: Intended Audience :: System Administrators
Classifier: Programming Language :: Python :: 2
Classifier: Programming Language :: Python :: 2.7
Classifier: Programming Language :: Python :: 3
Classifier: Programming Language :: Python :: 3.5
Classifier: Programming Language :: Python :: 3.6
Classifier: Programming Language :: Python :: 3.7
Requires-Dist: pyparsing
Requires-Dist: dateutils
Requires-Dist: ua-parser
Requires-Dist: user-agents
Requires-Dist: apache-log-parser
Requires-Dist: ConfigArgParse
